levin_videotools-0.0.6.data/data/default_config.yaml
videotools/__init__.py
videotools/main.py
videotools/video_text_clip.py
videotools/common/__init__.py
videotools/common/config.py
videotools/common/md5_sotre.py
videotools/common/stopwatch.py
videotools/common/video_tool.py
videotools/config/default_config.yaml
levin_videotools-0.0.6.dist-info/LICENSE.txt
levin_videotools-0.0.6.dist-info/METADATA
levin_videotools-0.0.6.dist-info/WHEEL
levin_videotools-0.0.6.dist-info/entry_points.txt
levin_videotools-0.0.6.dist-info/top_level.txt
levin_videotools-0.0.6.dist-info/RECORD
